richclub/__init__.py
richclub/rich_club_coefficient_degree.py
richclub/rich_club_coefficient_rank.py
richclub-1.0.2.dev1.dist-info/DESCRIPTION.rst
richclub-1.0.2.dev1.dist-info/METADATA
richclub-1.0.2.dev1.dist-info/RECORD
richclub-1.0.2.dev1.dist-info/WHEEL
richclub-1.0.2.dev1.dist-info/metadata.json
richclub-1.0.2.dev1.dist-info/top_level.txt
