Metadata-Version: 2.0
Name: richclub
Version: 1.0.2.dev1
Summary: Calculate the Rich Club Coefficient of a complex network
Home-page: https://github.com/HaoruoLiu/richclub
Author: Haoruo Liu
Author-email: haoruo.liu@qq.com
License: UNKNOWN
Platform: UNKNOWN
